{
    "Username-Password Combinations": {
        "informixuser": "informix", 
        "ron": "r0n", 
        "ron01": "ron01", 
        "ron02": "ron02", 
        "informix": "redhat", 
        "cvsroot": "cvsroot", 
        "developer": "developer", 
        "cmail": "cmail", 
        "ec2-user": "ec2-user", 
        "xbian": "raspberry", 
        "selenium": "selenium", 
        "send": "send", 
        "subversion": "subversion", 
        "cPanelInstall": "cPanelInstall", 
        "adm": "adm", 
        "custom": "custom", 
        "fax": "fax", 
        "ftpuser": "ftpuser", 
        "postgres": "postgres", 
        "olympus": "olympus123", 
        "devel": "devel", 
        "clouduser": "clouduser", 
        "anonymous": "anonymous", 
        "db2": "db2", 
        "db-upload": "db-upload", 
        "CVSROOT": "CVSROOT", 
        "eggdrop": "eggdrop", 
        "cms": "cms", 
        "dir": "dir", 
        "dir1": "dir1", 
        "cisco": "cisco", 
        "poker": "poker", 
        "jade": "j@d3", 
        "gary": "password", 
        "administrator": "administrator", 
        "qwer": "qwer", 
        "cs": "cs", 
        "intern": "intern123", 
        "ec2": "ec2", 
        "mirror": "mirror123", 
        "download": "download", 
        "tes": "tes123", 
        "gameserver": "gameserver", 
        "ebooks": "ebooks", 
        "tmp": "tmp", 
        "ftp": "ftp123", 
        "toto": "toto", 
        "vyatta": "vyatta", 
        "john": "john", 
        "hostmaster": "host", 
        "public": "public", 
        "stefan": "stefan2012", 
        "db2fenc": "db2fenc", 
        "db2user": "db2user", 
        "logout": "logout", 
        "carl": "carl123", 
        "db2das": "db2das", 
        "ftpadmin": "ftpadmin", 
        "db2inst1": "db2inst1", 
        "sshd": "sshd", 
        "reverse": "reverse", 
        "db2fenc1": "db2fenc1", 
        "admin": "12345", 
        "ftpsiteuser": "ftpsiteuser", 
        "david": "david", 
        "etc": "etc", 
        "anon": "anon", 
        "ftpclient": "ftpclient", 
        "backup": "backup", 
        "xbmc": "xbmc", 
        "user": "user", 
        "xyz": "xyz", 
        "johns": "johns", 
        "catchall": "catchall123", 
        "echo": "echo", 
        "email": "email", 
        "informix02": "informix02", 
        "steven": "steven!@#", 
        "operator": "operator", 
        "dnscache": "dnscache", 
        "mark": "m@rk", 
        "ecommerce": "ecommerce", 
        "git": "git", 
        "guest": "guest", 
        "support": "support", 
        "informixs": "informixs", 
        "msp": "msp", 
        "rons": "rons", 
        "pi": "raspberry", 
        "files": "files", 
        "ftptemp": "ftptemp", 
        "gccftp": "gccftp", 
        "company": "company", 
        "ts3srv": "ts3srv", 
        "caritas": "caritas123", 
        "firebird": "firebird", 
        "customer": "customer", 
        "coremail": "coremail", 
        "ronuser": "ron", 
        "kodi": "kodi", 
        "default": "default", 
        "fmaster": "fmaster", 
        "informix1": "informix1", 
        "cvs": "cvs", 
        "informix2": "informix2", 
        "ron2": "ron2", 
        "ron1": "ron1", 
        "root": "1", 
        "control": "control", 
        "testuser": "testuser", 
        "file": "file", 
        "disablesite": "disablesite", 
        "mirrors": "mirrors", 
        "demo": "P@ssw0rd", 
        "sample": "s4mpl3", 
        "PlcmSpIp": "PlcmSpIp", 
        "ftpscript": "ftpscript", 
        "gcc": "gcc", 
        "documents": "documents", 
        "develop": "develop", 
        "webdata": "web", 
        "guru": "guru", 
        "drivers": "drivers", 
        "couchdb": "couchdb", 
        "hadoop": "1", 
        "ens": "ens", 
        "test": "test", 
        "android": "android", 
        "ubnt": "ubnt", 
        "config": "config", 
        "data-uploader": "data-uploader", 
        "postmaster": "p0stm@$t3r", 
        "dnslog": "dnslog", 
        "downloads": "downloads", 
        "ebook": "ebook", 
        "informixtest": "informixtest", 
        "ftpshared": "ftpshared", 
        "uucp": "uucp", 
        "ftpguest": "ftpguest", 
        "cvsuser": "cvsuser", 
        "data": "data", 
        "rontest": "rontest", 
        "recovery": "recovery", 
        "a": "a", 
        "dummy": "dummy", 
        "database": "database", 
        "informix01": "informix01", 
        "cps": "cps123"
    }, 
    "SSH BRUTEFORCERS": {
        "39": "205.186.163.208", 
        "10": "193.104.41.171", 
        "203": "67.239.155.74", 
        "13": "80.82.64.134", 
        "272": "119.73.206.40", 
        "20": "75.145.35.82", 
        "24": "210.151.42.216", 
        "29": "93.220.50.92", 
        "31": "65.181.123.242"
    }, 
    "TOP USERNAMES": {
        "5": "steven", 
        "6": "test", 
        "7": "support", 
        "73": "ron", 
        "75": "informix", 
        "50": "admin", 
        "9": "mark", 
        "218": "root"
    }, 
    "TOP PASSWORDS": {
        "5": "ubnt", 
        "6": "default", 
        "7": "user", 
        "10": "root", 
        "11": "1234", 
        "12": "password", 
        "13": "test", 
        "14": "admin"
    }
}